redfish_protocol_validator/__init__.py
redfish_protocol_validator/accounts.py
redfish_protocol_validator/console_scripts.py
redfish_protocol_validator/constants.py
redfish_protocol_validator/protocol_details.py
redfish_protocol_validator/redfish_logo.py
redfish_protocol_validator/report.py
redfish_protocol_validator/resources.py
redfish_protocol_validator/security_details.py
redfish_protocol_validator/service_details.py
redfish_protocol_validator/service_requests.py
redfish_protocol_validator/service_responses.py
redfish_protocol_validator/sessions.py
redfish_protocol_validator/system_under_test.py
redfish_protocol_validator/utils.py
redfish_protocol_validator-1.3.0.dist-info/licenses/AUTHORS.md
redfish_protocol_validator-1.3.0.dist-info/licenses/LICENSE.md
redfish_protocol_validator-1.3.0.dist-info/METADATA
redfish_protocol_validator-1.3.0.dist-info/WHEEL
redfish_protocol_validator-1.3.0.dist-info/entry_points.txt
redfish_protocol_validator-1.3.0.dist-info/top_level.txt
redfish_protocol_validator-1.3.0.dist-info/RECORD
