Metadata-Version: 2.4
Name: redfish_protocol_validator
Version: 1.3.0
Summary: Redfish Protocol Validator
Home-page: https://github.com/DMTF/Redfish-Protocol-Validator
Author: DMTF, https://www.dmtf.org/standards/feedback
License: BSD 3-clause "New" or "Revised License"
Keywords: Redfish
Classifier: Development Status :: 5 - Production/Stable
Classifier: License :: OSI Approved :: BSD License
Classifier: Programming Language :: Python
Classifier: Topic :: Communications
License-File: LICENSE.md
License-File: AUTHORS.md
Requires-Dist: aenum
Requires-Dist: colorama
Requires-Dist: pyasn1
Requires-Dist: pyasn1-modules
Requires-Dist: requests>=2.30.0
Requires-Dist: sseclient-py
Requires-Dist: urllib3
Dynamic: author
Dynamic: classifier
Dynamic: description
Dynamic: description-content-type
Dynamic: home-page
Dynamic: keywords
Dynamic: license
Dynamic: license-file
Dynamic: requires-dist
Dynamic: summary
